[
    {
        "title": "PERFORMANCE ANALYST",
        "company": "Quest Global",
        "link": "https://in.linkedin.com/jobs/view/performance-analyst-at-quest-global-4425875199?position=1&pageNum=0&refId=H3l8uMwxkRPt29FaownPZA%3D%3D&trackingId=cILYS0%2Fl0EvievXoNsC%2BSg%3D%3D",
        "query": "\"Energy Analyst\" AND (Python OR \"Power BI\")"
    },
    {
        "title": "",
        "company": "",
        "link": "https://in.linkedin.com/jobs/view/system-analyst-at-quest-global-4422855868?position=2&pageNum=0&refId=H3l8uMwxkRPt29FaownPZA%3D%3D&trackingId=aI6Z%2BGrgjnbN5NnrjjHLAw%3D%3D",
        "query": "\"Energy Analyst\" AND (Python OR \"Power BI\")"
    },
    {
        "title": "",
        "company": "",
        "link": "https://in.linkedin.com/jobs/view/advisory-analyst-at-aurora-energy-research-4428020605?position=3&pageNum=0&refId=H3l8uMwxkRPt29FaownPZA%3D%3D&trackingId=4ce8TqJt0ZLlWRFOHofvqA%3D%3D",
        "query": "\"Energy Analyst\" AND (Python OR \"Power BI\")"
    },
    {
        "title": "",
        "company": "",
        "link": "https://in.linkedin.com/jobs/view/data-analyst-power-transformer-at-hitachi-energy-4437771276?position=4&pageNum=0&refId=H3l8uMwxkRPt29FaownPZA%3D%3D&trackingId=xiKnOsTnnh2imQ2gr5lkxg%3D%3D",
        "query": "\"Energy Analyst\" AND (Python OR \"Power BI\")"
    },
    {
        "title": "",
        "company": "",
        "link": "https://in.linkedin.com/jobs/view/energy-market-analyst-power-at-icf-4430926508?position=5&pageNum=0&refId=H3l8uMwxkRPt29FaownPZA%3D%3D&trackingId=g%2BuwI%2Fwr5OpbzooYsITXNA%3D%3D",
        "query": "\"Energy Analyst\" AND (Python OR \"Power BI\")"
    },
    {
        "title": "",
        "company": "",
        "link": "https://in.linkedin.com/jobs/view/data-scientist-energy-sector-at-workongrid-4436949514?position=6&pageNum=0&refId=H3l8uMwxkRPt29FaownPZA%3D%3D&trackingId=gDf717XF9FjHsy%2BuU%2B0HbA%3D%3D",
        "query": "\"Energy Analyst\" AND (Python OR \"Power BI\")"
    },
    {
        "title": "",
        "company": "",
        "link": "https://in.linkedin.com/jobs/view/business-analyst-data-%E2%80%93-power-market-at-gna-energy-4417151217?position=7&pageNum=0&refId=H3l8uMwxkRPt29FaownPZA%3D%3D&trackingId=o0caqH2Mb%2FrtuFjHRlT8Tw%3D%3D",
        "query": "\"Energy Analyst\" AND (Python OR \"Power BI\")"
    },
    {
        "title": "",
        "company": "",
        "link": "https://in.linkedin.com/jobs/view/energy-modelling-analyst-at-aurora-energy-research-4435052111?position=8&pageNum=0&refId=H3l8uMwxkRPt29FaownPZA%3D%3D&trackingId=Eppy%2B04NosfFTWLVzxNzBw%3D%3D",
        "query": "\"Energy Analyst\" AND (Python OR \"Power BI\")"
    },
    {
        "title": "",
        "company": "",
        "link": "https://in.linkedin.com/jobs/view/power-markets-associate-renewable-energy-at-enfinity-global-4439986306?position=9&pageNum=0&refId=H3l8uMwxkRPt29FaownPZA%3D%3D&trackingId=SJUDIEbVaNl61BvDUIrrrg%3D%3D",
        "query": "\"Energy Analyst\" AND (Python OR \"Power BI\")"
    },
    {
        "title": "",
        "company": "",
        "link": "https://in.linkedin.com/jobs/view/performance-analyst-ii-at-fluence-4440996952?position=10&pageNum=0&refId=H3l8uMwxkRPt29FaownPZA%3D%3D&trackingId=bfScCE6J3idt6zGw57uftg%3D%3D",
        "query": "\"Energy Analyst\" AND (Python OR \"Power BI\")"
    },
    {
        "title": "IN-Senior Associate_ Carbon/Green hydrogen_ Decarbonization_Advisory_Gurgaon",
        "company": "",
        "link": "https://in.linkedin.com/jobs/view/in-senior-associate-carbon-green-hydrogen-decarbonization-advisory-gurgaon-at-pwc-india-4291067237?position=1&pageNum=0&refId=OOx6uB3kHwBBoKyx8VcAKw%3D%3D&trackingId=qaytfX%2BwO0yE0TB8e9FMrw%3D%3D",
        "query": "\"Green Hydrogen\" AND (Analyst OR Research)"
    },
    {
        "title": "",
        "company": "",
        "link": "https://in.linkedin.com/jobs/view/in-senior-associate-renewables-decarbonisation-advisory-hyderabad-at-pwc-india-4436735015?position=2&pageNum=0&refId=OOx6uB3kHwBBoKyx8VcAKw%3D%3D&trackingId=AxdccsB%2Fv37xTGXXXEHq%2Fw%3D%3D",
        "query": "\"Green Hydrogen\" AND (Analyst OR Research)"
    },
    {
        "title": "",
        "company": "",
        "link": "https://in.linkedin.com/jobs/view/in-senior-associate-green-hydrogen-and-its-derivatives-decarbonisation-advisory-hyderabad-at-pwc-india-4291069002?position=3&pageNum=0&refId=OOx6uB3kHwBBoKyx8VcAKw%3D%3D&trackingId=TkAAnT3n7n6WavFW3gq59A%3D%3D",
        "query": "\"Green Hydrogen\" AND (Analyst OR Research)"
    },
    {
        "title": "",
        "company": "",
        "link": "https://in.linkedin.com/jobs/view/market-intelligence-data-analyst-%E2%80%93-solar%2Bbess-at-reliance-industries-limited-4435637687?position=4&pageNum=0&refId=OOx6uB3kHwBBoKyx8VcAKw%3D%3D&trackingId=wFaR6wQbkprg%2B2XH55R2qA%3D%3D",
        "query": "\"Green Hydrogen\" AND (Analyst OR Research)"
    },
    {
        "title": "",
        "company": "",
        "link": "https://in.linkedin.com/jobs/view/equity-research-associate-at-kavi-4437770605?position=5&pageNum=0&refId=OOx6uB3kHwBBoKyx8VcAKw%3D%3D&trackingId=s%2F0LvuEBQW69ISLn%2FdefDw%3D%3D",
        "query": "\"Green Hydrogen\" AND (Analyst OR Research)"
    },
    {
        "title": "",
        "company": "",
        "link": "https://in.linkedin.com/jobs/view/in-senior-associate-industrial-decarbonisation-decarbonization-advisory-bangalore-at-pwc-india-4438208590?position=6&pageNum=0&refId=OOx6uB3kHwBBoKyx8VcAKw%3D%3D&trackingId=T6ACnWeBNflwiy4jT22A7w%3D%3D",
        "query": "\"Green Hydrogen\" AND (Analyst OR Research)"
    },
    {
        "title": "",
        "company": "",
        "link": "https://in.linkedin.com/jobs/view/programme-lead-green-hydrogen-at-icf-4440251371?position=7&pageNum=0&refId=OOx6uB3kHwBBoKyx8VcAKw%3D%3D&trackingId=MT8bRlJ0BixiS7kEBVmTNw%3D%3D",
        "query": "\"Green Hydrogen\" AND (Analyst OR Research)"
    },
    {
        "title": "",
        "company": "",
        "link": "https://in.linkedin.com/jobs/view/mobility-thematic-expert-at-aspire-iitb-research-park-foundation-4437956700?position=8&pageNum=0&refId=OOx6uB3kHwBBoKyx8VcAKw%3D%3D&trackingId=Vjk4n1%2Fu5Jddv2auiTUZHQ%3D%3D",
        "query": "\"Green Hydrogen\" AND (Analyst OR Research)"
    },
    {
        "title": "",
        "company": "",
        "link": "https://in.linkedin.com/jobs/view/experimental-physicist-in-oulu-noida-at-amity-university-4427114649?position=9&pageNum=0&refId=OOx6uB3kHwBBoKyx8VcAKw%3D%3D&trackingId=wqCmWI6f2%2BmcxTini2KIzw%3D%3D",
        "query": "\"Green Hydrogen\" AND (Analyst OR Research)"
    },
    {
        "title": "",
        "company": "",
        "link": "https://in.linkedin.com/jobs/view/economic-industry-research-internship-in-chennai-at-energy-alternatives-india-4432889623?position=10&pageNum=0&refId=OOx6uB3kHwBBoKyx8VcAKw%3D%3D&trackingId=Ud6Ca5mDu%2Bw%2FHEC8nKpSyg%3D%3D",
        "query": "\"Green Hydrogen\" AND (Analyst OR Research)"
    },
    {
        "title": "Research Analyst",
        "company": "Council on Energy, Environment and Water (CEEW)",
        "link": "https://in.linkedin.com/jobs/view/research-analyst-at-council-on-energy-environment-and-water-ceew-4426488877?position=1&pageNum=0&refId=1b%2BKWJ%2F%2F5OYfAvGTq736OQ%3D%3D&trackingId=PB18lZ%2BuDqpgf0zudiHOSw%3D%3D",
        "query": "\"Renewable Energy\" AND (Research OR Analyst)"
    },
    {
        "title": "",
        "company": "",
        "link": "https://in.linkedin.com/jobs/view/power-markets-associate-renewable-energy-at-enfinity-global-4439986306?position=2&pageNum=0&refId=1b%2BKWJ%2F%2F5OYfAvGTq736OQ%3D%3D&trackingId=ipryQjgBvQ%2BeYfkT1MiPpA%3D%3D",
        "query": "\"Renewable Energy\" AND (Research OR Analyst)"
    },
    {
        "title": "",
        "company": "",
        "link": "https://in.linkedin.com/jobs/view/advisory-analyst-at-aurora-energy-research-4428020605?position=3&pageNum=0&refId=1b%2BKWJ%2F%2F5OYfAvGTq736OQ%3D%3D&trackingId=Wa4tR2JYAVdxyHTycPiLJg%3D%3D",
        "query": "\"Renewable Energy\" AND (Research OR Analyst)"
    },
    {
        "title": "",
        "company": "",
        "link": "https://in.linkedin.com/jobs/view/analyst-senior-analyst-low-carbon-transition-cpi-india-at-climate-policy-initiative-4437839128?position=4&pageNum=0&refId=1b%2BKWJ%2F%2F5OYfAvGTq736OQ%3D%3D&trackingId=08azxDmBddpb%2Bp4kDq6GfQ%3D%3D",
        "query": "\"Renewable Energy\" AND (Research OR Analyst)"
    },
    {
        "title": "",
        "company": "",
        "link": "https://in.linkedin.com/jobs/view/senior-research-analyst-at-wood-mackenzie-4435048215?position=5&pageNum=0&refId=1b%2BKWJ%2F%2F5OYfAvGTq736OQ%3D%3D&trackingId=fjIhNPmCRTFWekGL8Z1CHQ%3D%3D",
        "query": "\"Renewable Energy\" AND (Research OR Analyst)"
    },
    {
        "title": "",
        "company": "",
        "link": "https://in.linkedin.com/jobs/view/senior-research-analyst-global-power-market-at-wood-mackenzie-4390306274?position=6&pageNum=0&refId=1b%2BKWJ%2F%2F5OYfAvGTq736OQ%3D%3D&trackingId=B1ekqKdlN1RfD2WZwXjdZA%3D%3D",
        "query": "\"Renewable Energy\" AND (Research OR Analyst)"
    },
    {
        "title": "",
        "company": "",
        "link": "https://in.linkedin.com/jobs/view/energy-market-analyst-power-at-icf-4430933428?position=7&pageNum=0&refId=1b%2BKWJ%2F%2F5OYfAvGTq736OQ%3D%3D&trackingId=7yWhG%2FwF4vdCBLAY%2FKlwoQ%3D%3D",
        "query": "\"Renewable Energy\" AND (Research OR Analyst)"
    },
    {
        "title": "",
        "company": "",
        "link": "https://in.linkedin.com/jobs/view/energy-modelling-analyst-at-aurora-energy-research-4435052111?position=8&pageNum=0&refId=1b%2BKWJ%2F%2F5OYfAvGTq736OQ%3D%3D&trackingId=7OqpUKbtkARFLa4Aum3Yyg%3D%3D",
        "query": "\"Renewable Energy\" AND (Research OR Analyst)"
    },
    {
        "title": "",
        "company": "",
        "link": "https://in.linkedin.com/jobs/view/development-associate-at-cleantech-industry-resources-cir-4436173548?position=9&pageNum=0&refId=1b%2BKWJ%2F%2F5OYfAvGTq736OQ%3D%3D&trackingId=XgbEp57VpNxO%2Bb%2Fy5Gk6rA%3D%3D",
        "query": "\"Renewable Energy\" AND (Research OR Analyst)"
    },
    {
        "title": "",
        "company": "",
        "link": "https://in.linkedin.com/jobs/view/research-analyst-at-council-on-energy-environment-and-water-ceew-4438068727?position=10&pageNum=0&refId=1b%2BKWJ%2F%2F5OYfAvGTq736OQ%3D%3D&trackingId=EtAYI%2FChQoBZPvT%2BSfyyOQ%3D%3D",
        "query": "\"Renewable Energy\" AND (Research OR Analyst)"
    },
    {
        "title": "PERFORMANCE ANALYST",
        "company": "Quest Global",
        "link": "https://in.linkedin.com/jobs/view/performance-analyst-at-quest-global-4425851654?position=1&pageNum=0&refId=fJcMrD6olIH%2BTF1a9tXe5A%3D%3D&trackingId=qsZNIKK6tIPs07sKGMaI0w%3D%3D",
        "query": "\"Energy Data Analyst\""
    },
    {
        "title": "",
        "company": "",
        "link": "https://in.linkedin.com/jobs/view/system-analyst-at-quest-global-4422855868?position=2&pageNum=0&refId=fJcMrD6olIH%2BTF1a9tXe5A%3D%3D&trackingId=fqvRASqRpUg5uNBRdWgoIQ%3D%3D",
        "query": "\"Energy Data Analyst\""
    },
    {
        "title": "",
        "company": "",
        "link": "https://in.linkedin.com/jobs/view/data-analyst-power-transformer-at-hitachi-energy-4437771276?position=3&pageNum=0&refId=fJcMrD6olIH%2BTF1a9tXe5A%3D%3D&trackingId=Pu6dQ9G%2F86mZV0HXx%2Bp6Aw%3D%3D",
        "query": "\"Energy Data Analyst\""
    },
    {
        "title": "",
        "company": "",
        "link": "https://in.linkedin.com/jobs/view/energy-market-analyst-power-at-icf-4430933428?position=4&pageNum=0&refId=fJcMrD6olIH%2BTF1a9tXe5A%3D%3D&trackingId=oGnqL69bqdLMuQvQkQ0nKg%3D%3D",
        "query": "\"Energy Data Analyst\""
    },
    {
        "title": "",
        "company": "",
        "link": "https://in.linkedin.com/jobs/view/power-markets-associate-renewable-energy-at-enfinity-global-4439986306?position=5&pageNum=0&refId=fJcMrD6olIH%2BTF1a9tXe5A%3D%3D&trackingId=SkyDgrWyfGLV8v253ZEwjw%3D%3D",
        "query": "\"Energy Data Analyst\""
    },
    {
        "title": "",
        "company": "",
        "link": "https://in.linkedin.com/jobs/view/energy-market-analyst-power-at-icf-4429667169?position=6&pageNum=0&refId=fJcMrD6olIH%2BTF1a9tXe5A%3D%3D&trackingId=mJ%2BXP19GKOfhcKW76BfGkQ%3D%3D",
        "query": "\"Energy Data Analyst\""
    },
    {
        "title": "",
        "company": "",
        "link": "https://in.linkedin.com/jobs/view/advisory-analyst-at-aurora-energy-research-4428020605?position=7&pageNum=0&refId=fJcMrD6olIH%2BTF1a9tXe5A%3D%3D&trackingId=sNnDi1RECeAcd70St3HeWQ%3D%3D",
        "query": "\"Energy Data Analyst\""
    },
    {
        "title": "",
        "company": "",
        "link": "https://in.linkedin.com/jobs/view/performance-analyst-ii-at-fluence-4440996952?position=8&pageNum=0&refId=fJcMrD6olIH%2BTF1a9tXe5A%3D%3D&trackingId=gD5L9AX6bj6cBLD71cX86w%3D%3D",
        "query": "\"Energy Data Analyst\""
    },
    {
        "title": "",
        "company": "",
        "link": "https://in.linkedin.com/jobs/view/climate-data-analyst-at-msci-inc-4434844256?position=9&pageNum=0&refId=fJcMrD6olIH%2BTF1a9tXe5A%3D%3D&trackingId=OY%2Bm3SduE16trBVn%2BBrtug%3D%3D",
        "query": "\"Energy Data Analyst\""
    },
    {
        "title": "",
        "company": "",
        "link": "https://in.linkedin.com/jobs/view/business-analyst-data-%E2%80%93-power-market-at-gna-energy-4417151217?position=10&pageNum=0&refId=fJcMrD6olIH%2BTF1a9tXe5A%3D%3D&trackingId=JjzgZO9Qb14NFSVRQEZOdA%3D%3D",
        "query": "\"Energy Data Analyst\""
    },
    {
        "title": "GIS Automation Specialist",
        "company": "Wind Pioneers",
        "link": "https://in.linkedin.com/jobs/view/gis-automation-specialist-at-wind-pioneers-4398129096?position=1&pageNum=0&refId=WmMXBiGXsu4JeEBaakIvAA%3D%3D&trackingId=Yrbi0XtH3%2FqaeI9vta%2Fp6Q%3D%3D",
        "query": "\"GIS Analyst\" AND (\"Energy\" OR \"Renewables\")"
    },
    {
        "title": "",
        "company": "",
        "link": "https://in.linkedin.com/jobs/view/senior-gis-specialist-at-aecom-4430025033?position=2&pageNum=0&refId=WmMXBiGXsu4JeEBaakIvAA%3D%3D&trackingId=zpkPJrytRqoC4rL07KWylw%3D%3D",
        "query": "\"GIS Analyst\" AND (\"Energy\" OR \"Renewables\")"
    },
    {
        "title": "",
        "company": "",
        "link": "https://in.linkedin.com/jobs/view/implementation-specialist-gis-india-at-neara-4412628631?position=3&pageNum=0&refId=WmMXBiGXsu4JeEBaakIvAA%3D%3D&trackingId=5%2BUJZfvcm0%2FPyhfhrZ%2BR%2BQ%3D%3D",
        "query": "\"GIS Analyst\" AND (\"Energy\" OR \"Renewables\")"
    },
    {
        "title": "",
        "company": "",
        "link": "https://in.linkedin.com/jobs/view/engineering-services-associate-manager-at-accenture-in-india-4324711718?position=4&pageNum=0&refId=WmMXBiGXsu4JeEBaakIvAA%3D%3D&trackingId=hEvTYRmd3DyDFe018zHFSQ%3D%3D",
        "query": "\"GIS Analyst\" AND (\"Energy\" OR \"Renewables\")"
    },
    {
        "title": "",
        "company": "",
        "link": "https://in.linkedin.com/jobs/view/gis-specialist-mapping-survey123-webapp-at-erm-4425755083?position=5&pageNum=0&refId=WmMXBiGXsu4JeEBaakIvAA%3D%3D&trackingId=uBa7QG3IbgMec0519FDGPA%3D%3D",
        "query": "\"GIS Analyst\" AND (\"Energy\" OR \"Renewables\")"
    },
    {
        "title": "",
        "company": "",
        "link": "https://in.linkedin.com/jobs/view/sr-gis-developer-at-quest-global-4402393129?position=6&pageNum=0&refId=WmMXBiGXsu4JeEBaakIvAA%3D%3D&trackingId=74iGnJXCoGZD5yDV0hyw4Q%3D%3D",
        "query": "\"GIS Analyst\" AND (\"Energy\" OR \"Renewables\")"
    },
    {
        "title": "",
        "company": "",
        "link": "https://in.linkedin.com/jobs/view/power-markets-associate-renewable-energy-at-enfinity-global-4439986306?position=7&pageNum=0&refId=WmMXBiGXsu4JeEBaakIvAA%3D%3D&trackingId=h7BmwCzf9g33usuhrhcKnQ%3D%3D",
        "query": "\"GIS Analyst\" AND (\"Energy\" OR \"Renewables\")"
    },
    {
        "title": "",
        "company": "",
        "link": "https://in.linkedin.com/jobs/view/implementation-specialist-gis-india-at-neara-4412628632?position=8&pageNum=0&refId=WmMXBiGXsu4JeEBaakIvAA%3D%3D&trackingId=KuysdmGTxxjBfaC7ObRfUw%3D%3D",
        "query": "\"GIS Analyst\" AND (\"Energy\" OR \"Renewables\")"
    },
    {
        "title": "",
        "company": "",
        "link": "https://in.linkedin.com/jobs/view/system-analyst-at-quest-global-4422855868?position=9&pageNum=0&refId=WmMXBiGXsu4JeEBaakIvAA%3D%3D&trackingId=mFvJFKq5ekv0gHXHAm%2FSNQ%3D%3D",
        "query": "\"GIS Analyst\" AND (\"Energy\" OR \"Renewables\")"
    },
    {
        "title": "",
        "company": "",
        "link": "https://in.linkedin.com/jobs/view/gis-analyst-blr-at-burns-mcdonnell-india-4439422384?position=10&pageNum=0&refId=WmMXBiGXsu4JeEBaakIvAA%3D%3D&trackingId=RaOziDWO4Kvmd7o8MDCWpw%3D%3D",
        "query": "\"GIS Analyst\" AND (\"Energy\" OR \"Renewables\")"
    }
]